fips203.py
fips203-0.4.1.dist-info/METADATA
fips203-0.4.1.dist-info/WHEEL
fips203-0.4.1.dist-info/top_level.txt
fips203-0.4.1.dist-info/RECORD
