Metadata-Version: 2.1
Name: fips203
Version: 0.4.1
Summary: ML-KEM (FIPS203) -- asymmetric, quantum-secure encryption
Author-email: Daniel Kahn Gillmor <dkg@fifthhorseman.net>
Project-URL: Homepage, https://github.com/integritychain/fips203/tree/main/ffi/python
Project-URL: Repository, https://github.com/integritychain/fips203.git
Project-URL: Issues, https://github.com/integritychain/fips203/issues
Keywords: cryptography,encryption,FIPS,FIPS203,KEM,lattice,module-lattice,post-quantum
Classifier: Development Status :: 4 - Beta
Classifier: Intended Audience :: Developers
Classifier: Intended Audience :: Telecommunications Industry
Classifier: Intended Audience :: Information Technology
Classifier: Topic :: Security :: Cryptography
Classifier: License :: OSI Approved :: MIT License
Classifier: License :: DFSG approved
Classifier: Programming Language :: Python :: 3
Classifier: Programming Language :: Python :: 3.9
Classifier: Programming Language :: Python :: 3.10
Classifier: Programming Language :: Python :: 3.11
Classifier: Programming Language :: Python :: 3.12
Classifier: Programming Language :: Python :: 3.13
